showtens/__init__.py
showtens/images.py
showtens/imports.py
showtens/util.py
showtens/videos.py
showtens-0.3.1.dist-info/METADATA
showtens-0.3.1.dist-info/WHEEL
showtens-0.3.1.dist-info/top_level.txt
showtens-0.3.1.dist-info/RECORD
