Metadata-Version: 2.1
Name: showtens
Version: 0.3.1
Summary: Visualize torch tensors EASILY.
Author-email: Vassilis Papadopoulos <vassilis.physics@gmail.com>
License: MIT License
Project-URL: Homepage, https://github.com/frotaur/showtens
Project-URL: Bug Tracker, https://github.com/frotaur/showtens/issues
Classifier: Programming Language :: Python :: 3
Classifier: License :: OSI Approved :: MIT License
Classifier: Operating System :: OS Independent
Classifier: Development Status :: 3 - Alpha
Requires-Python: >=3.9
Requires-Dist: matplotlib
Requires-Dist: opencv-python
Requires-Dist: numpy
